OpUstad/__init__.py
OpUstad/__main__.py
OpUstad/utils.py
OpUstad-1.9.21.dist-info/DESCRIPTION.rst
OpUstad-1.9.21.dist-info/METADATA
OpUstad-1.9.21.dist-info/RECORD
OpUstad-1.9.21.dist-info/WHEEL
OpUstad-1.9.21.dist-info/metadata.json
OpUstad-1.9.21.dist-info/top_level.txt
