Metadata-Version: 2.0
Name: OpUstad
Version: 1.9.21
Summary: OpUstad
Home-page: https://github.com/Ustad-Op
Author: Ustad-Op
Author-email: jtatagaga@gmail.com
License: UNKNOWN
Platform: UNKNOWN
Classifier: Programming Language :: Python :: 3
Classifier: License :: OSI Approved :: MIT License
Classifier: Operating System :: OS Independent
Requires-Dist: cryptg
Requires-Dist: gitpython (==3.1.18)
Requires-Dist: heroku3 (==4.2.3)
Requires-Dist: psycopg2 (==2.9.1)
Requires-Dist: python-decouple (==3.4)
Requires-Dist: sqlalchemy (==1.3.20)
Requires-Dist: telethon (==1.13.0)
